mlogitviz/__init__.py
mlogitviz/exceptions.py
mlogitviz/model.py
mlogitviz/visualization.py
mlogitviz-0.1.5.dist-info/METADATA
mlogitviz-0.1.5.dist-info/WHEEL
mlogitviz-0.1.5.dist-info/top_level.txt
mlogitviz-0.1.5.dist-info/RECORD
