Metadata-Version: 2.2
Name: mlogitviz
Version: 0.1.5
Summary: A library to compute and visualize marginal effects for multinomial logistic regression models
Home-page: https://github.com/payamv3/mlogitviz
Author: Payam Saeedi and Eric Williams
Author-email: ps4019@rit.edu
Classifier: Programming Language :: Python :: 3
Classifier: License :: OSI Approved :: MIT License
Classifier: Operating System :: OS Independent
Requires-Python: >=3.6
Requires-Dist: pandas
Requires-Dist: numpy
Requires-Dist: statsmodels
Requires-Dist: matplotlib
Requires-Dist: seaborn
Dynamic: author
Dynamic: author-email
Dynamic: classifier
Dynamic: description
Dynamic: description-content-type
Dynamic: home-page
Dynamic: requires-dist
Dynamic: requires-python
Dynamic: summary
